austin_tui/__init__.py
austin_tui/__main__.py
austin_tui/adapters.py
austin_tui/controller.py
austin_tui/model/__init__.py
austin_tui/model/austin.py
austin_tui/model/system.py
austin_tui/view/__init__.py
austin_tui/view/austin.py
austin_tui/view/palette.py
austin_tui/view/tui.austinui
austin_tui/widgets/__init__.py
austin_tui/widgets/box.py
austin_tui/widgets/catalog.py
austin_tui/widgets/command_bar.py
austin_tui/widgets/graph.py
austin_tui/widgets/label.py
austin_tui/widgets/markup.py
austin_tui/widgets/scroll.py
austin_tui/widgets/selector.py
austin_tui/widgets/table.py
austin_tui/widgets/window.py
austin_tui-1.4.1.dist-info/METADATA
austin_tui-1.4.1.dist-info/WHEEL
austin_tui-1.4.1.dist-info/entry_points.txt
austin_tui-1.4.1.dist-info/licenses/LICENSE.md
austin_tui-1.4.1.dist-info/RECORD
