Metadata-Version: 2.4
Name: austin-tui
Version: 1.4.1
Summary: The top-like text-based user interface for Austin
Project-URL: documentation, https://austin-tui.readthedocs.io
Project-URL: homepage, https://github.com/P403n1x87/austin-tui
Project-URL: issues, https://github.com/P403n1x87/austin-tui/issues
Project-URL: repository, https://github.com/P403n1x87/austin-tui
Author-email: "Gabriele N. Tornetta" <phoenix1987@gmail.com>
License-Expression: GPL-3.0-or-later
License-File: LICENSE.md
Keywords: development,performance,profiling,testing
Classifier: Development Status :: 5 - Production/Stable
Classifier: Intended Audience :: Developers
Classifier: License :: OSI Approved :: GNU General Public License v3 or later (GPLv3+)
Classifier: Programming Language :: Python :: 3.9
Classifier: Programming Language :: Python :: 3.10
Classifier: Programming Language :: Python :: 3.11
Classifier: Programming Language :: Python :: 3.12
Classifier: Programming Language :: Python :: 3.13
Requires-Python: >=3.9
Requires-Dist: austin-python~=2.1
Requires-Dist: importlib-resources~=5.10
Requires-Dist: lxml~=5.0
Requires-Dist: psutil
Requires-Dist: windows-curses~=2.1; sys_platform == 'win32'
